rillrate_py-0.1.1.dist-info/METADATA
rillrate_py-0.1.1.dist-info/WHEEL
rillrate/__init__.py
rillrate/expansion.py
rillrate/rillrate.cpython-39-x86_64-linux-gnu.so
rillrate_py-0.1.1.dist-info/RECORD
