Metadata-Version: 2.1
Name: rillrate-py
Version: 0.1.1
Summary: Python bindings for RillRate
Keywords: logging
Home-Page: https://github.com/rate-technology/rillrate-py
Author: Denis Kolodin <deniskolodin@gmail.com>, overfloat <rillrate@gmail.com>
Author-Email: Denis Kolodin <deniskolodin@gmail.com>, overfloat <rillrate@gmail.com>
License: MIT/Apache-2.0
